predictionrevisited.py
predictionrevisited-1.0.0.dist-info/LICENSE.md
predictionrevisited-1.0.0.dist-info/METADATA
predictionrevisited-1.0.0.dist-info/WHEEL
predictionrevisited-1.0.0.dist-info/top_level.txt
predictionrevisited-1.0.0.dist-info/RECORD
