Metadata-Version: 2.1
Name: predictionrevisited
Version: 1.0.0
Summary: Prediction Revisited module for observation-based prediction
Home-page: https://www.predictionrevisited.com
Author: Megan Czasonis and David Turkington
License: MIT
License-File: LICENSE.md
Requires-Dist: numpy
Requires-Dist: pandas
